mailtrace/__init__.py
mailtrace/__main__.py
mailtrace/config.py
mailtrace/log.py
mailtrace/models.py
mailtrace/parser.py
mailtrace/utils.py
mailtrace/aggregator/__init__.py
mailtrace/aggregator/base.py
mailtrace/aggregator/opensearch.py
mailtrace/aggregator/ssh_host.py
mailtrace-0.2.0.dist-info/METADATA
mailtrace-0.2.0.dist-info/WHEEL
mailtrace-0.2.0.dist-info/entry_points.txt
mailtrace-0.2.0.dist-info/top_level.txt
mailtrace-0.2.0.dist-info/RECORD
