Metadata-Version: 2.4
Name: mailtrace
Version: 0.2.0
Author-email: SiriusKoan <me@siriuskoan.one>
Requires-Dist: click>=8.2.1
Requires-Dist: opensearch-py>=3.0.0
Requires-Dist: paramiko>=3.5.1
Requires-Dist: pyyaml>=6.0.2
